cli/__init__.py
cli/app.py
cli/commands/__init__.py
cli/commands/changelog.py
cli/commands/component.py
cli/commands/config.py
cli/commands/product.py
cli/commands/releaseNote.py
cli/commands/stats.py
cli/services/__init__.py
cli/services/bitbucket_service.py
cli/services/confluence_service.py
cli/services/jira_service.py
cli/services/powerbi_service.py
cli/services/sonarqube_service.py
cli/services/stats_service.py
cli/utils/__init__.py
cli/utils/configuration_manager.py
cli/utils/csv_util.py
atlcli-0.2.1.dist-info/LICENSE
atlcli-0.2.1.dist-info/METADATA
atlcli-0.2.1.dist-info/WHEEL
atlcli-0.2.1.dist-info/entry_points.txt
atlcli-0.2.1.dist-info/top_level.txt
atlcli-0.2.1.dist-info/RECORD
